rwkv_paddle/__init__.py
rwkv_paddle/model.py
rwkv_paddle/serialization.py
rwkv_paddle/utils.py
rwkv_paddle/cuda/operators.cu
rwkv_paddle/cuda/wrapper.cpp
rwkv_paddle-0.7.3.1.dist-info/LICENSE
rwkv_paddle-0.7.3.1.dist-info/METADATA
rwkv_paddle-0.7.3.1.dist-info/WHEEL
rwkv_paddle-0.7.3.1.dist-info/top_level.txt
rwkv_paddle-0.7.3.1.dist-info/RECORD
