Metadata-Version: 2.1
Name: rwkv-paddle
Version: 0.7.3.1
Summary: The RWKV Language Model on PaddlePaddle
Author: HighCWu
Project-URL: Homepage, https://github.com/HighCWu/rwkv-paddle
Project-URL: Bug Tracker, https://github.com/HighCWu/rwkv-paddle/issues
Classifier: Programming Language :: Python :: 3
Classifier: License :: OSI Approved :: Apache Software License
Classifier: Operating System :: OS Independent
Requires-Python: >=3.7
License-File: LICENSE
Requires-Dist: tokenizers (>=0.13.2)
